server.py
mcp_server_glitchtip-1.0.0.dist-info/METADATA
mcp_server_glitchtip-1.0.0.dist-info/WHEEL
mcp_server_glitchtip-1.0.0.dist-info/entry_points.txt
mcp_server_glitchtip-1.0.0.dist-info/RECORD
