Metadata-Version: 2.4
Name: mcp-server-glitchtip
Version: 1.0.0
Summary: MCP server enabling LLMs to query issues, stacktraces, and resolve errors in GlitchTip
Project-URL: Homepage, https://github.com/hffmnnj/mcp-server-glitchtip
Project-URL: Repository, https://github.com/hffmnnj/mcp-server-glitchtip
Project-URL: Issues, https://github.com/hffmnnj/mcp-server-glitchtip/issues
Author: hffmnnj
License: MIT
Keywords: ai,claude,debugging,error-tracking,glitchtip,llm,mcp,sentry
Classifier: Development Status :: 4 - Beta
Classifier: Intended Audience :: Developers
Classifier: License :: OSI Approved :: MIT License
Classifier: Programming Language :: Python :: 3
Classifier: Programming Language :: Python :: 3.10
Classifier: Programming Language :: Python :: 3.11
Classifier: Programming Language :: Python :: 3.12
Classifier: Topic :: Software Development :: Debuggers
Requires-Python: >=3.10
Requires-Dist: httpx>=0.27.0
Requires-Dist: mcp>=1.0.0
